{
  "results": [
    {
      "id": "rerun-chrome-web-store-jnloekndgehbebkkaehndhihcpoliaal-4",
      "status": "review",
      "hard_gate": "pass",
      "ux": {
        "beginner": "fail",
        "intermediate": "pass",
        "expert": "pass"
      },
      "reason": "카드 이동을 반복해 스콜피온 규칙을 적용하고 완성 여부를 보여주는 흐름은 구체적이지만 제목만으로 사용 문제와 결과가 충분히 드러나지 않는다.",
      "risk_flags": [
        "title_unclear"
      ]
    },
    {
      "id": "rerun-chrome-web-store-jnloekndgehbebkkaehndhihcpoliaal-5",
      "status": "review",
      "hard_gate": "pass",
      "ux": {
        "beginner": "fail",
        "intermediate": "pass",
        "expert": "pass"
      },
      "reason": "카드 이동을 반복해 완성 여부를 확인하고 한국어 규칙 요약을 제공하지만 제목만으로 문제와 결과가 명확하지 않다.",
      "risk_flags": [
        "title_unclear"
      ]
    },
    {
      "id": "rerun-chrome-web-store-jnloekndgehbebkkaehndhihcpoliaal-6",
      "status": "review",
      "hard_gate": "pass",
      "ux": {
        "beginner": "fail",
        "intermediate": "pass",
        "expert": "pass"
      },
      "reason": "카드 이동을 반복해 스콜피온 한 판의 완성 여부를 보여주는 흐름은 가능하지만 제목만으로 문제와 결과가 충분히 보이지 않는다.",
      "risk_flags": [
        "title_unclear"
      ]
    },
    {
      "id": "rerun-chrome-web-store-jnloekndgehbebkkaehndhihcpoliaal-7",
      "status": "review",
      "hard_gate": "pass",
      "ux": {
        "beginner": "fail",
        "intermediate": "pass",
        "expert": "pass"
      },
      "reason": "카드 이동을 반복해 규칙을 적용하고 완성 여부를 보여주며 한국어 요약을 제공하지만 제목만으로 사용 목적과 결과가 불명확하다.",
      "risk_flags": [
        "title_unclear"
      ]
    },
    {
      "id": "rerun-chrome-web-store-jnloekndgehbebkkaehndhihcpoliaal-8",
      "status": "review",
      "hard_gate": "pass",
      "ux": {
        "beginner": "fail",
        "intermediate": "pass",
        "expert": "pass"
      },
      "reason": "카드 이동을 반복해 한 판의 완성 여부를 확인하는 구조는 구체적이지만 제목만으로 문제와 결과가 충분히 드러나지 않는다.",
      "risk_flags": [
        "title_unclear"
      ]
    },
    {
      "id": "rerun-chrome-web-store-jnloekndgehbebkkaehndhihcpoliaal-9",
      "status": "review",
      "hard_gate": "pass",
      "ux": {
        "beginner": "fail",
        "intermediate": "pass",
        "expert": "pass"
      },
      "reason": "카드 이동을 반복해 짧은 스콜피온 게임의 완성 여부를 보여주는 구조는 가능하지만 제목만으로 결과가 명확하지 않다.",
      "risk_flags": [
        "title_unclear"
      ]
    },
    {
      "id": "rerun-chrome-web-store-jnloekndhihcpoliaal-10",
      "status": "review",
      "hard_gate": "pass",
      "ux": {
        "beginner": "fail",
        "intermediate": "pass",
        "expert": "pass"
      },
      "reason": "카드 이동을 반복해 규칙 적용과 완성 여부를 제공하는 흐름은 자연스럽지만 제목만으로 사용 문제와 결과가 드러나지 않는다.",
      "risk_flags": [
        "title_unclear"
      ]
    },
    {
      "id": "rerun-chrome-web-store-jnloekndhihcpoliaal-11",
      "status": "review",
      "hard_gate": "pass",
      "ux": {
        "beginner": "fail",
        "intermediate": "pass",
        "expert": "pass"
      },
      "reason": "카드 이동을 반복해 완성 여부를 확인하고 한국어 규칙을 보여주지만 제목만으로 문제와 결과가 명확하지 않다.",
      "risk_flags": [
        "title_unclear"
      ]
    },
    {
      "id": "rerun-chrome-web-store-jnloekndhihcpoliaal-12",
      "status": "review",
      "hard_gate": "pass",
      "ux": {
        "beginner": "fail",
        "intermediate": "pass",
        "expert": "pass"
      },
      "reason": "카드 이동을 반복해 짧은 한 판의 완성 여부를 보여주는 흐름은 구체적이나 제목만으로 사용 목적과 결과가 불명확하다.",
      "risk_flags": [
        "title_unclear"
      ]
    },
    {
      "id": "rerun-chrome-web-store-jnloekndhihcpoliaal-13",
      "status": "review",
      "hard_gate": "pass",
      "ux": {
        "beginner": "fail",
        "intermediate": "pass",
        "expert": "pass"
      },
      "reason": "카드 이동을 반복해 스콜피온 규칙과 완성 결과를 제공하는 구조는 가능하지만 제목만으로 문제와 결과가 충분히 보이지 않는다.",
      "risk_flags": [
        "title_unclear"
      ]
    },
    {
      "id": "rerun-chrome-web-store-jnloekndhihcpoliaal-14",
      "status": "review",
      "hard_gate": "pass",
      "ux": {
        "beginner": "fail",
        "intermediate": "pass",
        "expert": "pass"
      },
      "reason": "카드 이동을 반복해 한 판의 완성 여부를 보여주는 흐름은 구체적이지만 제목만으로 결과가 명확하지 않다.",
      "risk_flags": [
        "title_unclear"
      ]
    },
    {
      "id": "rerun-chrome-web-store-jnloekndhihcpoliaal-15",
      "status": "review",
      "hard_gate": "pass",
      "ux": {
        "beginner": "fail",
        "intermediate": "pass",
        "expert": "pass"
      },
      "reason": "카드 이동을 반복해 스콜피온 게임 결과를 보여주고 짧은 모드를 제공하지만 제목만으로 문제와 결과가 충분히 드러나지 않는다.",
      "risk_flags": [
        "title_unclear"
      ]
    },
    {
      "id": "rerun-chrome-web-store-jnloekndhihcpoliaal-16",
      "status": "review",
      "hard_gate": "pass",
      "ux": {
        "beginner": "fail",
        "intermediate": "pass",
        "expert": "pass"
      },
      "reason": "카드 이동을 반복해 규칙을 적용하고 완성 여부를 보여주는 구조는 가능하나 제목만으로 사용 목적과 결과가 불명확하다.",
      "risk_flags": [
        "title_unclear"
      ]
    },
    {
      "id": "rerun-chrome-web-store-jnloekndhihcpoliaal-17",
      "status": "review",
      "hard_gate": "pass",
      "ux": {
        "beginner": "fail",
        "intermediate": "pass",
        "expert": "pass"
      },
      "reason": "카드 이동을 반복해 한 판의 완성 여부를 보여주는 흐름은 자연스럽지만 제목만으로 문제와 결과가 충분히 보이지 않는다.",
      "risk_flags": [
        "title_unclear"
      ]
    },
    {
      "id": "rerun-chrome-web-store-kdlfddjhmdfcdepdagbjlcodpolmmkki-0",
      "status": "fail",
      "hard_gate": "fail",
      "ux": {
        "beginner": "fail",
        "intermediate": "fail",
        "expert": "fail"
      },
      "reason": "자동차 선택과 반복적인 레이싱 조작이라는 복수 입력을 처리해 결승선 결과를 내므로 입력 1개·처리 1회 조건을 위반한다.",
      "risk_flags": [
        "multi_input",
        "repeated_interaction"
      ]
    },
    {
      "id": "rerun-chrome-web-store-kdlfddjhmdfcdepdagbjlcodpolmmkki-1",
      "status": "fail",
      "hard_gate": "fail",
      "ux": {
        "beginner": "fail",
        "intermediate": "fail",
        "expert": "fail"
      },
      "reason": "자동차 선택과 반복적인 레이싱 조작을 모두 요구하므로 한 번의 입력으로 한 결과를 내는 세로 조각 조건을 충족하지 못한다.",
      "risk_flags": [
        "multi_input",
        "repeated_interaction"
      ]
    },
    {
      "id": "rerun-chrome-web-store-kdlfddjhmdfcdepdagbjlcodpolmmkki-2",
      "status": "fail",
      "hard_gate": "fail",
      "ux": {
        "beginner": "fail",
        "intermediate": "fail",
        "expert": "fail"
      },
      "reason": "차량 선택 뒤 여러 번의 조작으로 레이스를 진행해야 하므로 입력 1개·처리 1회·결과 1개 구조가 아니다.",
      "risk_flags": [
        "multi_input",
        "repeated_interaction"
      ]
    },
    {
      "id": "rerun-chrome-web-store-kdlfddjhmdfcdepdagbjlcodpolmmkki-3",
      "status": "fail",
      "hard_gate": "fail",
      "ux": {
        "beginner": "fail",
        "intermediate": "fail",
        "expert": "fail"
      },
      "reason": "자동차 선택과 반복 조작이 필요한 레이싱 게임이라 단일 입력으로 결승 결과를 산출하는 조건을 위반한다.",
      "risk_flags": [
        "multi_input",
        "repeated_interaction"
      ]
    },
    {
      "id": "rerun-chrome-web-store-kdlfddjhmdfcdepdagbjlcodpolmmkki-4",
      "status": "fail",
      "hard_gate": "fail",
      "ux": {
        "beginner": "fail",
        "intermediate": "fail",
        "expert": "fail"
      },
      "reason": "차량 선택 후 반복적인 레이싱 조작이 필요해 입력 1개·처리 1회·결과 1개 요건에 맞지 않는다.",
      "risk_flags": [
        "multi_input",
        "repeated_interaction"
      ]
    },
    {
      "id": "rerun-chrome-web-store-kdlfddjhmdfcdepdagbjlcodpolmmkki-5",
      "status": "fail",
      "hard_gate": "fail",
      "ux": {
        "beginner": "fail",
        "intermediate": "fail",
        "expert": "fail"
      },
      "reason": "자동차 선택과 레이스 중 조작을 모두 요구하므로 한 번의 입력으로 승자 결과를 만드는 카드 조합이 아니다.",
      "risk_flags": [
        "multi_input",
        "repeated_interaction"
      ]
    },
    {
      "id": "rerun-chrome-web-store-kdlfddjhmdfcdepdagbjlcodpolmmkki-6",
      "status": "fail",
      "hard_gate": "fail",
      "ux": {
        "beginner": "fail",
        "intermediate": "fail",
        "expert": "fail"
      },
      "reason": "차량 선택과 반복 운전 조작이 함께 필요해 단일 입력·단일 처리·단일 결과 조건을 충족하지 못한다.",
      "risk_flags": [
        "multi_input",
        "repeated_interaction"
      ]
    },
    {
      "id": "rerun-chrome-web-store-kdlfddjhmdfcdepdagbjlcodpolmmkki-7",
      "status": "fail",
      "hard_gate": "fail",
      "ux": {
        "beginner": "fail",
        "intermediate": "fail",
        "expert": "fail"
      },
      "reason": "자동차 선택과 반복 레이싱 조작으로 결승 결과를 내는 구조라 입력 1개·처리 1회 조건을 위반한다.",
      "risk_flags": [
        "multi_input",
        "repeated_interaction"
      ]
    },
    {
      "id": "rerun-chrome-web-store-kdlfddjhmdfcdepdagbjlcodpolmmkki-8",
      "status": "fail",
      "hard_gate": "fail",
      "ux": {
        "beginner": "fail",
        "intermediate": "fail",
        "expert": "fail"
      },
      "reason": "차량 선택 뒤 지속적인 조작이 필요하므로 짧은 한 판이라도 단일 입력 처리 조각으로 축소되지 않는다.",
      "risk_flags": [
        "multi_input",
        "repeated_interaction"
      ]
    },
    {
      "id": "rerun-chrome-web-store-kdlfddjhmdfcdepdagbjlcodpolmmkki-9",
      "status": "fail",
      "hard_gate": "fail",
      "ux": {
        "beginner": "fail",
        "intermediate": "fail",
        "expert": "fail"
      },
      "reason": "자동차 선택과 반복적인 레이싱 조작이 필수라 한 번의 입력으로 결승 결과를 제공하는 조건에 맞지 않는다.",
      "risk_flags": [
        "multi_input",
        "repeated_interaction"
      ]
    },
    {
      "id": "rerun-chrome-web-store-kdlfddjhmdfcdepdagbjlcodpolmmkki-10",
      "status": "fail",
      "hard_gate": "fail",
      "ux": {
        "beginner": "fail",
        "intermediate": "fail",
        "expert": "fail"
      },
      "reason": "차량 선택 후 여러 조작을 거쳐야 드리프트 점수와 순위가 나오므로 입력 1개·처리 1회 조건을 위반한다.",
      "risk_flags": [
        "multi_input",
        "repeated_interaction"
      ]
    },
    {
      "id": "rerun-chrome-web-store-kdlfddjhmdfcdepdagbjlcodpolmmkki-11",
      "status": "fail",
      "hard_gate": "fail",
      "ux": {
        "beginner": "fail",
        "intermediate": "fail",
        "expert": "fail"
      },
      "reason": "자동차 선택과 반복 운전 조작이 모두 필요해 단일 입력으로 결승 결과를 내는 구조가 아니다.",
      "risk_flags": [
        "multi_input",
        "repeated_interaction"
      ]
    },
    {
      "id": "rerun-chrome-web-store-kdlfddjhmdfcdepdagbjlcodpolmmkki-12",
      "status": "fail",
      "hard_gate": "fail",
      "ux": {
        "beginner": "fail",
        "intermediate": "fail",
        "expert": "fail"
      },
      "reason": "차량 선택과 레이싱 중 지속 조작을 요구하므로 1개 입력·1회 처리·1개 결과 조건을 충족하지 못한다.",
      "risk_flags": [
        "multi_input",
        "repeated_interaction"
      ]
    },
    {
      "id": "rerun-chrome-web-store-kdlfddjhmdfcdepdagbjlcodpolmmkki-13",
      "status": "fail",
      "hard_gate": "fail",
      "ux": {
        "beginner": "fail",
        "intermediate": "fail",
        "expert": "fail"
      },
      "reason": "자동차 선택 뒤 반복적인 레이스 조작이 필요해 결승 결과만 즉시 내는 세로 조각이 아니다.",
      "risk_flags": [
        "multi_input",
        "repeated_interaction"
      ]
    },
    {
      "id": "rerun-chrome-web-store-kdlfddjhmdfcdepdagbjlcodpolmmkki-14",
      "status": "fail",
      "hard_gate": "fail",
      "ux": {
        "beginner": "fail",
        "intermediate": "fail",
        "expert": "fail"
      },
      "reason": "차량 선택과 여러 차례의 레이싱 조작을 모두 요구하므로 단일 입력 처리 조건을 위반한다.",
      "risk_flags": [
        "multi_input",
        "repeated_interaction"
      ]
    },
    {
      "id": "rerun-chrome-web-store-kdlfddjhmdfcdepdagbjlcodpolmmkki-15",
      "status": "fail",
      "hard_gate": "fail",
      "ux": {
        "beginner": "fail",
        "intermediate": "fail",
        "expert": "fail"
      },
      "reason": "자동차 선택과 반복 조작이 필요한 레이싱 게임이라 입력 1개·처리 1회·결과 1개 기준에 맞지 않는다.",
      "risk_flags": [
        "multi_input",
        "repeated_interaction"
      ]
    },
    {
      "id": "rerun-chrome-web-store-kdlfddjhmdfcdepdagbjlcodpolmmkki-16",
      "status": "fail",
      "hard_gate": "fail",
      "ux": {
        "beginner": "fail",
        "intermediate": "fail",
        "expert": "fail"
      },
      "reason": "차량을 고른 뒤 레이스를 반복 조작해야 하므로 한 번의 입력으로 승자 결과를 내는 카드가 아니다.",
      "risk_flags": [
        "multi_input",
        "repeated_interaction"
      ]
    },
    {
      "id": "rerun-chrome-web-store-kdlfddjhmdfcdepdagbjlcodpolmmkki-17",
      "status": "fail",
      "hard_gate": "fail",
      "ux": {
        "beginner": "fail",
        "intermediate": "fail",
        "expert": "fail"
      },
      "reason": "자동차 선택과 지속적인 레이싱 조작이 함께 필요해 단일 입력·단일 처리·단일 결과 요건을 위반한다.",
      "risk_flags": [
        "multi_input",
        "repeated_interaction"
      ]
    },
    {
      "id": "rerun-app-store-373493387-0",
      "status": "review",
      "hard_gate": "pass",
      "ux": {
        "beginner": "fail",
        "intermediate": "pass",
        "expert": "pass"
      },
      "reason": "플래시카드 콘텐츠를 입력해 복습 일정을 계산하고 다음 카드와 시점을 보여주는 흐름은 가능하지만 제목만으로 문제와 결과가 불명확하고 동기화 전제가 남는다.",
      "risk_flags": [
        "title_unclear",
        "sync_ambiguity"
      ]
    },
    {
      "id": "rerun-app-store-373493387-1",
      "status": "review",
      "hard_gate": "pass",
      "ux": {
        "beginner": "fail",
        "intermediate": "pass",
        "expert": "pass"
      },
      "reason": "카드 파일을 입력해 다음 복습 카드와 시점을 계산하는 구조는 허용되지만 PC에서 만든 자료와 모바일 불러오기라는 사전 준비가 필요하다.",
      "risk_flags": [
        "title_unclear",
        "prior_content_required"
      ]
    },
    {
      "id": "rerun-app-store-373493387-2",
      "status": "review",
      "hard_gate": "pass",
      "ux": {
        "beginner": "fail",
        "intermediate": "pass",
        "expert": "pass"
      },
      "reason": "플래시카드 콘텐츠에서 복습 시점을 계산하는 흐름은 구체적이나 제목만으로 문제와 결과가 보이지 않고 기존 학습 이력이 암묵적으로 필요하다.",
      "risk_flags": [
        "title_unclear",
        "history_required"
      ]
    },
    {
      "id": "rerun-app-store-373493387-3",
      "status": "review",
      "hard_gate": "pass",
      "ux": {
        "beginner": "fail",
        "intermediate": "pass",
        "expert": "pass"
      },
      "reason": "카드 콘텐츠를 입력해 다음 복습 카드와 시점을 산출하는 구조는 가능하지만 PC 제작 카드의 사전 준비와 제목의 결과 불명확성이 남는다.",
      "risk_flags": [
        "title_unclear",
        "prior_content_required"
      ]
    },
    {
      "id": "rerun-app-store-373493387-4",
      "status": "review",
      "hard_gate": "pass",
      "ux": {
        "beginner": "fail",
        "intermediate": "pass",
        "expert": "pass"
      },
      "reason": "카드 파일을 받아 복습 일정을 계산하는 흐름은 구체적이지만 모바일 불러오기를 위해 기존 PC 카드와 동기화 맥락이 필요하다.",
      "risk_flags": [
        "title_unclear",
        "sync_ambiguity"
      ]
    },
    {
      "id": "rerun-app-store-373493387-5",
      "status": "review",
      "hard_gate": "pass",
      "ux": {
        "beginner": "fail",
        "intermediate": "pass",
        "expert": "pass"
      },
      "reason": "플래시카드 콘텐츠에서 오늘 복습 목록과 다음 시점을 제공할 수 있으나 제목만으로 사용 문제와 결과가 충분히 드러나지 않는다.",
      "risk_flags": [
        "title_unclear"
      ]
    },
    {
      "id": "rerun-app-store-373493387-6",
      "status": "review",
      "hard_gate": "pass",
      "ux": {
        "beginner": "fail",
        "intermediate": "pass",
        "expert": "pass"
      },
      "reason": "카드 콘텐츠를 입력해 복습 시점을 계산하는 구조는 자연스럽지만 기존 학습 이력과 제목의 결과 불명확성이 남아 있다.",
      "risk_flags": [
        "title_unclear",
        "history_required"
      ]
    },
    {
      "id": "rerun-app-store-373493387-7",
      "status": "review",
      "hard_gate": "pass",
      "ux": {
        "beginner": "fail",
        "intermediate": "pass",
        "expert": "pass"
      },
      "reason": "PC 카드 파일을 입력해 모바일에서 다음 복습 카드와 시점을 보여줄 수 있지만 사전 카드 제작과 동기화 전제가 있다.",
      "risk_flags": [
        "title_unclear",
        "prior_content_required"
      ]
    },
    {
      "id": "rerun-app-store-373493387-8",
      "status": "review",
      "hard_gate": "pass",
      "ux": {
        "beginner": "fail",
        "intermediate": "pass",
        "expert": "pass"
      },
      "reason": "카드 파일을 처리해 복습 일정을 산출하는 흐름은 가능하나 PC 자료와 모바일 이동이라는 사전 준비가 필요하다.",
      "risk_flags": [
        "title_unclear",
        "sync_ambiguity"
      ]
    },
    {
      "id": "rerun-app-store-373493387-9",
      "status": "review",
      "hard_gate": "pass",
      "ux": {
        "beginner": "fail",
        "intermediate": "pass",
        "expert": "pass"
      },
      "reason": "기존 카드 파일을 입력해 다음 복습 카드와 시점을 제공하는 구조는 가능하지만 사전 카드 제작과 제목의 결과 불명확성이 남는다.",
      "risk_flags": [
        "title_unclear",
        "prior_content_required"
      ]
    },
    {
      "id": "rerun-app-store-373493387-10",
      "status": "review",
      "hard_gate": "pass",
      "ux": {
        "beginner": "fail",
        "intermediate": "pass",
        "expert": "pass"
      },
      "reason": "카드 콘텐츠에서 복습 일정을 계산할 수 있으나 모바일 동기화 맥락과 제목만으로 결과가 드러나지 않는 문제가 있다.",
      "risk_flags": [
        "title_unclear",
        "sync_ambiguity"
      ]
    },
    {
      "id": "rerun-app-store-373493387-11",
      "status": "review",
      "hard_gate": "pass",
      "ux": {
        "beginner": "fail",
        "intermediate": "pass",
        "expert": "pass"
      },
      "reason": "카드 콘텐츠를 입력해 오늘 목록과 다음 복습 시점을 보여주는 흐름은 가능하지만 제목의 문제·결과 표현이 부족하다.",
      "risk_flags": [
        "title_unclear"
      ]
    },
    {
      "id": "rerun-app-store-373493387-12",
      "status": "review",
      "hard_gate": "pass",
      "ux": {
        "beginner": "fail",
        "intermediate": "pass",
        "expert": "pass"
      },
      "reason": "플래시카드 콘텐츠에서 복습 시점을 산출하는 구조는 자연스럽지만 제목만으로 문제와 결과가 명확하지 않고 학습 이력이 필요하다.",
      "risk_flags": [
        "title_unclear",
        "history_required"
      ]
    },
    {
      "id": "rerun-app-store-373493387-13",
      "status": "review",
      "hard_gate": "pass",
      "ux": {
        "beginner": "fail",
        "intermediate": "pass",
        "expert": "pass"
      },
      "reason": "카드 콘텐츠를 처리해 오늘 복습 목록과 다음 시점을 제공할 수 있으나 제목만으로 결과가 드러나지 않는다.",
      "risk_flags": [
        "title_unclear"
      ]
    },
    {
      "id": "rerun-app-store-373493387-14",
      "status": "review",
      "hard_gate": "pass",
      "ux": {
        "beginner": "fail",
        "intermediate": "pass",
        "expert": "pass"
      },
      "reason": "카드 파일을 입력해 복습 일정을 계산하는 흐름은 가능하지만 기존 PC 카드와 모바일 이동이라는 사전 준비가 요구된다.",
      "risk_flags": [
        "title_unclear",
        "prior_content_required"
      ]
    },
    {
      "id": "rerun-app-store-373493387-15",
      "status": "review",
      "hard_gate": "pass",
      "ux": {
        "beginner": "fail",
        "intermediate": "pass",
        "expert": "pass"
      },
      "reason": "플래시카드 콘텐츠에서 다음 복습 카드와 시점을 산출할 수 있으나 제목만으로 문제와 결과가 충분히 보이지 않는다.",
      "risk_flags": [
        "title_unclear"
      ]
    },
    {
      "id": "rerun-app-store-373493387-16",
      "status": "review",
      "hard_gate": "pass",
      "ux": {
        "beginner": "fail",
        "intermediate": "pass",
        "expert": "pass"
      },
      "reason": "PC 카드 파일을 입력해 모바일 복습 일정을 제공하는 구조는 가능하지만 카드 제작과 불러오기라는 사전 준비가 필요하다.",
      "risk_flags": [
        "title_unclear",
        "prior_content_required"
      ]
    },
    {
      "id": "rerun-app-store-373493387-17",
      "status": "review",
      "hard_gate": "pass",
      "ux": {
        "beginner": "fail",
        "intermediate": "pass",
        "expert": "pass"
      },
      "reason": "카드 콘텐츠에서 망각 전 복습 시점을 계산하는 흐름은 구체적이나 제목의 문제·결과 표현이 부족하고 학습 이력이 암묵적으로 필요하다.",
      "risk_flags": [
        "title_unclear",
        "history_required"
      ]
    }
  ]
}